{
  "generated_at": "2026-05-08 15:33:02",
  "eval_horizon": "5m",
  "baseline": {
    "samples": 1247,
    "entries": 1068,
    "coverage": 0.8565,
    "directional_accuracy": 0.4213,
    "win_rate": 0.5056,
    "avg_pnl_pts": -0.0066,
    "total_pnl_pts": -7.1,
    "avg_confidence": 0.6318
  },
  "enhanced": {
    "samples": 1247,
    "entries": 1068,
    "coverage": 0.8565,
    "directional_accuracy": 0.4204,
    "win_rate": 0.5047,
    "avg_pnl_pts": -0.01,
    "total_pnl_pts": -10.7,
    "avg_confidence": 0.6317
  },
  "changed_count": 72,
  "flat_conversions": 0,
  "blocked_count": 1,
  "changed_examples": [
    {
      "ts": "2026-05-08 13:34:00",
      "baseline_direction": 1,
      "baseline_confidence": 0.425,
      "enhanced_direction": 1,
      "enhanced_confidence": 0.4272,
      "actual": -1,
      "enhanced_pnl_pts": -2.5,
      "gate_reason": "soft_adjust",
      "gate_strength": 0.053934
    },
    {
      "ts": "2026-05-08 13:35:00",
      "baseline_direction": -1,
      "baseline_confidence": 0.85,
      "enhanced_direction": -1,
      "enhanced_confidence": 0.8515,
      "actual": -1,
      "enhanced_pnl_pts": 2.599999999999909,
      "gate_reason": "soft_adjust",
      "gate_strength": 0.055339
    },
    {
      "ts": "2026-05-08 13:36:00",
      "baseline_direction": -1,
      "baseline_confidence": 0.5375,
      "enhanced_direction": -1,
      "enhanced_confidence": 0.5382,
      "actual": -1,
      "enhanced_pnl_pts": 2.349999999999909,
      "gate_reason": "soft_adjust",
      "gate_strength": 0.017044
    },
    {
      "ts": "2026-05-08 13:37:00",
      "baseline_direction": 1,
      "baseline_confidence": 0.45,
      "enhanced_direction": 1,
      "enhanced_confidence": 0.4515,
      "actual": -1,
      "enhanced_pnl_pts": -1.5,
      "gate_reason": "soft_adjust",
      "gate_strength": 0.037785
    },
    {
      "ts": "2026-05-08 13:38:00",
      "baseline_direction": -1,
      "baseline_confidence": 0.9,
      "enhanced_direction": -1,
      "enhanced_confidence": 0.7947,
      "actual": -1,
      "enhanced_pnl_pts": 2.1499999999998636,
      "gate_reason": "blocked_by_microstructure",
      "gate_strength": -0.282451
    },
    {
      "ts": "2026-05-08 13:40:00",
      "baseline_direction": -1,
      "baseline_confidence": 0.8927,
      "enhanced_direction": -1,
      "enhanced_confidence": 0.8921,
      "actual": 0,
      "enhanced_pnl_pts": 0.4500000000000455,
      "gate_reason": "soft_adjust",
      "gate_strength": -0.014464
    },
    {
      "ts": "2026-05-08 13:41:00",
      "baseline_direction": -1,
      "baseline_confidence": 0.8875,
      "enhanced_direction": -1,
      "enhanced_confidence": 0.8833,
      "actual": 0,
      "enhanced_pnl_pts": -0.09999999999990905,
      "gate_reason": "soft_adjust",
      "gate_strength": -0.104223
    },
    {
      "ts": "2026-05-08 13:43:00",
      "baseline_direction": -1,
      "baseline_confidence": 0.8927,
      "enhanced_direction": -1,
      "enhanced_confidence": 0.8957,
      "actual": 1,
      "enhanced_pnl_pts": -1.4500000000000455,
      "gate_reason": "soft_adjust",
      "gate_strength": 0.074892
    },
    {
      "ts": "2026-05-08 13:44:00",
      "baseline_direction": -1,
      "baseline_confidence": 0.5375,
      "enhanced_direction": -1,
      "enhanced_confidence": 0.5341,
      "actual": 1,
      "enhanced_pnl_pts": -2.9500000000000455,
      "gate_reason": "soft_adjust",
      "gate_strength": -0.086132
    },
    {
      "ts": "2026-05-08 13:45:00",
      "baseline_direction": -1,
      "baseline_confidence": 0.65,
      "enhanced_direction": -1,
      "enhanced_confidence": 0.6565,
      "actual": 1,
      "enhanced_pnl_pts": -2.2000000000000455,
      "gate_reason": "soft_adjust",
      "gate_strength": 0.162416
    },
    {
      "ts": "2026-05-08 13:46:00",
      "baseline_direction": -1,
      "baseline_confidence": 0.45,
      "enhanced_direction": -1,
      "enhanced_confidence": 0.447,
      "actual": 1,
      "enhanced_pnl_pts": -3.849999999999909,
      "gate_reason": "soft_adjust",
      "gate_strength": -0.07405
    },
    {
      "ts": "2026-05-08 13:47:00",
      "baseline_direction": -1,
      "baseline_confidence": 0.75,
      "enhanced_direction": -1,
      "enhanced_confidence": 0.7505,
      "actual": 1,
      "enhanced_pnl_pts": -4.550000000000182,
      "gate_reason": "soft_adjust",
      "gate_strength": 0.013128
    },
    {
      "ts": "2026-05-08 13:48:00",
      "baseline_direction": 1,
      "baseline_confidence": 0.55,
      "enhanced_direction": 1,
      "enhanced_confidence": 0.555,
      "actual": 1,
      "enhanced_pnl_pts": 3.699999999999818,
      "gate_reason": "soft_adjust",
      "gate_strength": 0.126173
    },
    {
      "ts": "2026-05-08 13:49:00",
      "baseline_direction": 1,
      "baseline_confidence": 0.5,
      "enhanced_direction": 1,
      "enhanced_confidence": 0.5031,
      "actual": 1,
      "enhanced_pnl_pts": 2.2999999999999545,
      "gate_reason": "soft_adjust",
      "gate_strength": 0.077113
    },
    {
      "ts": "2026-05-08 13:50:00",
      "baseline_direction": 1,
      "baseline_confidence": 0.4333,
      "enhanced_direction": 1,
      "enhanced_confidence": 0.4307,
      "actual": 1,
      "enhanced_pnl_pts": 2.3999999999998636,
      "gate_reason": "soft_adjust",
      "gate_strength": -0.065659
    },
    {
      "ts": "2026-05-08 13:51:00",
      "baseline_direction": 1,
      "baseline_confidence": 0.7,
      "enhanced_direction": 1,
      "enhanced_confidence": 0.7011,
      "actual": 1,
      "enhanced_pnl_pts": 0.650000000000091,
      "gate_reason": "soft_adjust",
      "gate_strength": 0.028736
    },
    {
      "ts": "2026-05-08 13:52:00",
      "baseline_direction": 1,
      "baseline_confidence": 0.775,
      "enhanced_direction": 1,
      "enhanced_confidence": 0.7772,
      "actual": -1,
      "enhanced_pnl_pts": -0.5,
      "gate_reason": "soft_adjust",
      "gate_strength": 0.054623
    },
    {
      "ts": "2026-05-08 13:53:00",
      "baseline_direction": 1,
      "baseline_confidence": 0.8583,
      "enhanced_direction": 1,
      "enhanced_confidence": 0.8631,
      "actual": -1,
      "enhanced_pnl_pts": -1.6499999999998636,
      "gate_reason": "soft_adjust",
      "gate_strength": 0.118054
    },
    {
      "ts": "2026-05-08 13:54:00",
      "baseline_direction": 1,
      "baseline_confidence": 0.7833,
      "enhanced_direction": 1,
      "enhanced_confidence": 0.7888,
      "actual": -1,
      "enhanced_pnl_pts": -0.6000000000001364,
      "gate_reason": "soft_adjust",
      "gate_strength": 0.136348
    },
    {
      "ts": "2026-05-08 13:55:00",
      "baseline_direction": 1,
      "baseline_confidence": 0.725,
      "enhanced_direction": 1,
      "enhanced_confidence": 0.7226,
      "actual": 1,
      "enhanced_pnl_pts": 1.300000000000182,
      "gate_reason": "soft_adjust",
      "gate_strength": -0.059414
    },
    {
      "ts": "2026-05-08 13:57:00",
      "baseline_direction": 1,
      "baseline_confidence": 0.5083,
      "enhanced_direction": 1,
      "enhanced_confidence": 0.5012,
      "actual": 1,
      "enhanced_pnl_pts": 1.949999999999818,
      "gate_reason": "soft_adjust",
      "gate_strength": -0.178603
    },
    {
      "ts": "2026-05-08 13:58:00",
      "baseline_direction": -1,
      "baseline_confidence": 0.4875,
      "enhanced_direction": -1,
      "enhanced_confidence": 0.494,
      "actual": 1,
      "enhanced_pnl_pts": -1.7000000000000455,
      "gate_reason": "soft_adjust",
      "gate_strength": 0.16353
    },
    {
      "ts": "2026-05-08 13:59:00",
      "baseline_direction": 1,
      "baseline_confidence": 0.6,
      "enhanced_direction": 1,
      "enhanced_confidence": 0.6081,
      "actual": 1,
      "enhanced_pnl_pts": 0.75,
      "gate_reason": "soft_adjust",
      "gate_strength": 0.202901
    },
    {
      "ts": "2026-05-08 14:00:00",
      "baseline_direction": 1,
      "baseline_confidence": 0.85,
      "enhanced_direction": 1,
      "enhanced_confidence": 0.8528,
      "actual": 0,
      "enhanced_pnl_pts": 0.0,
      "gate_reason": "soft_adjust",
      "gate_strength": 0.106214
    },
    {
      "ts": "2026-05-08 14:01:00",
      "baseline_direction": 1,
      "baseline_confidence": 0.775,
      "enhanced_direction": 1,
      "enhanced_confidence": 0.7739,
      "actual": 1,
      "enhanced_pnl_pts": 0.75,
      "gate_reason": "soft_adjust",
      "gate_strength": -0.027607
    },
    {
      "ts": "2026-05-08 14:02:00",
      "baseline_direction": 1,
      "baseline_confidence": 0.8,
      "enhanced_direction": 1,
      "enhanced_confidence": 0.8069,
      "actual": 1,
      "enhanced_pnl_pts": 1.2000000000000455,
      "gate_reason": "soft_adjust",
      "gate_strength": 0.171438
    },
    {
      "ts": "2026-05-08 14:03:00",
      "baseline_direction": 1,
      "baseline_confidence": 0.45,
      "enhanced_direction": 1,
      "enhanced_confidence": 0.4499,
      "actual": 1,
      "enhanced_pnl_pts": 1.949999999999818,
      "gate_reason": "soft_adjust",
      "gate_strength": -0.002764
    },
    {
      "ts": "2026-05-08 14:05:00",
      "baseline_direction": 1,
      "baseline_confidence": 0.65,
      "enhanced_direction": 1,
      "enhanced_confidence": 0.6486,
      "actual": -1,
      "enhanced_pnl_pts": -0.6000000000001364,
      "gate_reason": "soft_adjust",
      "gate_strength": -0.03595
    },
    {
      "ts": "2026-05-08 14:07:00",
      "baseline_direction": 1,
      "baseline_confidence": 0.8926,
      "enhanced_direction": 1,
      "enhanced_confidence": 0.8918,
      "actual": 0,
      "enhanced_pnl_pts": 0.0,
      "gate_reason": "soft_adjust",
      "gate_strength": -0.021102
    },
    {
      "ts": "2026-05-08 14:08:00",
      "baseline_direction": 1,
      "baseline_confidence": 0.75,
      "enhanced_direction": 1,
      "enhanced_confidence": 0.7446,
      "actual": 1,
      "enhanced_pnl_pts": 0.5500000000001819,
      "gate_reason": "soft_adjust",
      "gate_strength": -0.133916
    },
    {
      "ts": "2026-05-08 14:10:00",
      "baseline_direction": -1,
      "baseline_confidence": 0.575,
      "enhanced_direction": -1,
      "enhanced_confidence": 0.5808,
      "actual": 1,
      "enhanced_pnl_pts": -3.5499999999999545,
      "gate_reason": "soft_adjust",
      "gate_strength": 0.146192
    },
    {
      "ts": "2026-05-08 14:13:00",
      "baseline_direction": 1,
      "baseline_confidence": 0.8926,
      "enhanced_direction": 1,
      "enhanced_confidence": 0.8881,
      "actual": 1,
      "enhanced_pnl_pts": 3.849999999999909,
      "gate_reason": "soft_adjust",
      "gate_strength": -0.113376
    },
    {
      "ts": "2026-05-08 14:14:00",
      "baseline_direction": 1,
      "baseline_confidence": 0.7,
      "enhanced_direction": 1,
      "enhanced_confidence": 0.7008,
      "actual": 1,
      "enhanced_pnl_pts": 3.0,
      "gate_reason": "soft_adjust",
      "gate_strength": 0.0282
    },
    {
      "ts": "2026-05-08 14:15:00",
      "baseline_direction": 1,
      "baseline_confidence": 0.55,
      "enhanced_direction": 1,
      "enhanced_confidence": 0.5544,
      "actual": 1,
      "enhanced_pnl_pts": 1.900000000000091,
      "gate_reason": "soft_adjust",
      "gate_strength": 0.109629
    },
    {
      "ts": "2026-05-08 14:16:00",
      "baseline_direction": 1,
      "baseline_confidence": 0.8,
      "enhanced_direction": 1,
      "enhanced_confidence": 0.8005,
      "actual": 1,
      "enhanced_pnl_pts": 1.349999999999909,
      "gate_reason": "soft_adjust",
      "gate_strength": 0.018303
    },
    {
      "ts": "2026-05-08 14:17:00",
      "baseline_direction": 1,
      "baseline_confidence": 0.65,
      "enhanced_direction": 1,
      "enhanced_confidence": 0.6522,
      "actual": 0,
      "enhanced_pnl_pts": -0.25,
      "gate_reason": "soft_adjust",
      "gate_strength": 0.054741
    },
    {
      "ts": "2026-05-08 14:18:00",
      "baseline_direction": 1,
      "baseline_confidence": 0.7,
      "enhanced_direction": 1,
      "enhanced_confidence": 0.7044,
      "actual": 0,
      "enhanced_pnl_pts": 0.34999999999990905,
      "gate_reason": "soft_adjust",
      "gate_strength": 0.152854
    },
    {
      "ts": "2026-05-08 14:19:00",
      "baseline_direction": 1,
      "baseline_confidence": 0.7333,
      "enhanced_direction": 1,
      "enhanced_confidence": 0.726,
      "actual": 1,
      "enhanced_pnl_pts": 1.599999999999909,
      "gate_reason": "soft_adjust",
      "gate_strength": -0.182467
    },
    {
      "ts": "2026-05-08 14:20:00",
      "baseline_direction": 1,
      "baseline_confidence": 0.4,
      "enhanced_direction": 1,
      "enhanced_confidence": 0.3978,
      "actual": 0,
      "enhanced_pnl_pts": 0.40000000000009095,
      "gate_reason": "soft_adjust",
      "gate_strength": -0.055384
    },
    {
      "ts": "2026-05-08 14:21:00",
      "baseline_direction": 1,
      "baseline_confidence": 0.75,
      "enhanced_direction": 1,
      "enhanced_confidence": 0.747,
      "actual": -1,
      "enhanced_pnl_pts": -0.6999999999998181,
      "gate_reason": "soft_adjust",
      "gate_strength": -0.074662
    },
    {
      "ts": "2026-05-08 14:22:00",
      "baseline_direction": 1,
      "baseline_confidence": 0.7833,
      "enhanced_direction": 1,
      "enhanced_confidence": 0.7858,
      "actual": -1,
      "enhanced_pnl_pts": -2.0,
      "gate_reason": "soft_adjust",
      "gate_strength": 0.061777
    },
    {
      "ts": "2026-05-08 14:23:00",
      "baseline_direction": 1,
      "baseline_confidence": 0.6,
      "enhanced_direction": 1,
      "enhanced_confidence": 0.5974,
      "actual": -1,
      "enhanced_pnl_pts": -3.099999999999909,
      "gate_reason": "soft_adjust",
      "gate_strength": -0.066227
    },
    {
      "ts": "2026-05-08 14:24:00",
      "baseline_direction": 1,
      "baseline_confidence": 0.75,
      "enhanced_direction": 1,
      "enhanced_confidence": 0.7465,
      "actual": -1,
      "enhanced_pnl_pts": -3.5499999999999545,
      "gate_reason": "soft_adjust",
      "gate_strength": -0.086352
    },
    {
      "ts": "2026-05-08 14:25:00",
      "baseline_direction": 1,
      "baseline_confidence": 0.75,
      "enhanced_direction": 1,
      "enhanced_confidence": 0.7451,
      "actual": 0,
      "enhanced_pnl_pts": 0.34999999999990905,
      "gate_reason": "soft_adjust",
      "gate_strength": -0.122271
    },
    {
      "ts": "2026-05-08 14:26:00",
      "baseline_direction": 1,
      "baseline_confidence": 0.45,
      "enhanced_direction": 1,
      "enhanced_confidence": 0.4438,
      "actual": 0,
      "enhanced_pnl_pts": 0.25,
      "gate_reason": "soft_adjust",
      "gate_strength": -0.155228
    },
    {
      "ts": "2026-05-08 14:27:00",
      "baseline_direction": -1,
      "baseline_confidence": 0.5,
      "enhanced_direction": -1,
      "enhanced_confidence": 0.5053,
      "actual": 1,
      "enhanced_pnl_pts": -1.25,
      "gate_reason": "soft_adjust",
      "gate_strength": 0.131502
    },
    {
      "ts": "2026-05-08 14:28:00",
      "baseline_direction": 1,
      "baseline_confidence": 0.3833,
      "enhanced_direction": -1,
      "enhanced_confidence": 0.3849,
      "actual": 1,
      "enhanced_pnl_pts": -1.7999999999999545,
      "gate_reason": "soft_adjust",
      "gate_strength": -0.196806
    },
    {
      "ts": "2026-05-08 14:29:00",
      "baseline_direction": 1,
      "baseline_confidence": 0.4167,
      "enhanced_direction": 1,
      "enhanced_confidence": 0.4173,
      "actual": 1,
      "enhanced_pnl_pts": 2.7000000000000455,
      "gate_reason": "soft_adjust",
      "gate_strength": 0.015973
    },
    {
      "ts": "2026-05-08 14:30:00",
      "baseline_direction": -1,
      "baseline_confidence": 0.3334,
      "enhanced_direction": -1,
      "enhanced_confidence": 0.3387,
      "actual": -1,
      "enhanced_pnl_pts": 0.650000000000091,
      "gate_reason": "soft_adjust",
      "gate_strength": 0.132775
    },
    {
      "ts": "2026-05-08 14:32:00",
      "baseline_direction": 1,
      "baseline_confidence": 0.7,
      "enhanced_direction": 1,
      "enhanced_confidence": 0.6979,
      "actual": 1,
      "enhanced_pnl_pts": 1.4500000000000455,
      "gate_reason": "soft_adjust",
      "gate_strength": -0.052992
    },
    {
      "ts": "2026-05-08 14:33:00",
      "baseline_direction": -1,
      "baseline_confidence": 0.505,
      "enhanced_direction": -1,
      "enhanced_confidence": 0.503,
      "actual": 1,
      "enhanced_pnl_pts": -0.7000000000000455,
      "gate_reason": "soft_adjust",
      "gate_strength": -0.050786
    },
    {
      "ts": "2026-05-08 14:34:00",
      "baseline_direction": -1,
      "baseline_confidence": 0.68,
      "enhanced_direction": -1,
      "enhanced_confidence": 0.6767,
      "actual": 0,
      "enhanced_pnl_pts": 0.25,
      "gate_reason": "soft_adjust",
      "gate_strength": -0.081663
    },
    {
      "ts": "2026-05-08 14:35:00",
      "baseline_direction": -1,
      "baseline_confidence": 0.41,
      "enhanced_direction": -1,
      "enhanced_confidence": 0.4069,
      "actual": 1,
      "enhanced_pnl_pts": -0.6000000000001364,
      "gate_reason": "soft_adjust",
      "gate_strength": -0.07848
    },
    {
      "ts": "2026-05-08 14:36:00",
      "baseline_direction": -1,
      "baseline_confidence": 0.3433,
      "enhanced_direction": -1,
      "enhanced_confidence": 0.3446,
      "actual": 0,
      "enhanced_pnl_pts": 0.10000000000013642,
      "gate_reason": "soft_adjust",
      "gate_strength": 0.031284
    },
    {
      "ts": "2026-05-08 14:37:00",
      "baseline_direction": 1,
      "baseline_confidence": 0.465,
      "enhanced_direction": 1,
      "enhanced_confidence": 0.4684,
      "actual": 1,
      "enhanced_pnl_pts": 1.349999999999909,
      "gate_reason": "soft_adjust",
      "gate_strength": 0.084492
    },
    {
      "ts": "2026-05-08 14:38:00",
      "baseline_direction": 1,
      "baseline_confidence": 0.75,
      "enhanced_direction": 1,
      "enhanced_confidence": 0.7489,
      "actual": 1,
      "enhanced_pnl_pts": 2.400000000000091,
      "gate_reason": "soft_adjust",
      "gate_strength": -0.027473
    },
    {
      "ts": "2026-05-08 14:39:00",
      "baseline_direction": 1,
      "baseline_confidence": 0.6,
      "enhanced_direction": 1,
      "enhanced_confidence": 0.6043,
      "actual": 1,
      "enhanced_pnl_pts": 2.5,
      "gate_reason": "soft_adjust",
      "gate_strength": 0.106923
    },
    {
      "ts": "2026-05-08 14:40:00",
      "baseline_direction": 1,
      "baseline_confidence": 0.4167,
      "enhanced_direction": 1,
      "enhanced_confidence": 0.4098,
      "actual": 1,
      "enhanced_pnl_pts": 1.0499999999999545,
      "gate_reason": "soft_adjust",
      "gate_strength": -0.172579
    },
    {
      "ts": "2026-05-08 14:41:00",
      "baseline_direction": 1,
      "baseline_confidence": 0.8,
      "enhanced_direction": 1,
      "enhanced_confidence": 0.8011,
      "actual": 1,
      "enhanced_pnl_pts": 1.0,
      "gate_reason": "soft_adjust",
      "gate_strength": 0.041668
    },
    {
      "ts": "2026-05-08 14:42:00",
      "baseline_direction": -1,
      "baseline_confidence": 0.4967,
      "enhanced_direction": -1,
      "enhanced_confidence": 0.4943,
      "actual": 0,
      "enhanced_pnl_pts": 0.20000000000004547,
      "gate_reason": "soft_adjust",
      "gate_strength": -0.059054
    },
    {
      "ts": "2026-05-08 14:43:00",
      "baseline_direction": 1,
      "baseline_confidence": 0.43,
      "enhanced_direction": 1,
      "enhanced_confidence": 0.4368,
      "actual": 0,
      "enhanced_pnl_pts": -0.15000000000009095,
      "gate_reason": "soft_adjust",
      "gate_strength": 0.16967
    },
    {
      "ts": "2026-05-08 14:44:00",
      "baseline_direction": 1,
      "baseline_confidence": 0.9,
      "enhanced_direction": 1,
      "enhanced_confidence": 0.9021,
      "actual": -1,
      "enhanced_pnl_pts": -1.150000000000091,
      "gate_reason": "soft_adjust",
      "gate_strength": 0.053403
    },
    {
      "ts": "2026-05-08 14:45:00",
      "baseline_direction": 1,
      "baseline_confidence": 0.545,
      "enhanced_direction": 1,
      "enhanced_confidence": 0.5439,
      "actual": 0,
      "enhanced_pnl_pts": 0.049999999999954525,
      "gate_reason": "soft_adjust",
      "gate_strength": -0.026363
    },
    {
      "ts": "2026-05-08 14:46:00",
      "baseline_direction": 1,
      "baseline_confidence": 0.67,
      "enhanced_direction": 1,
      "enhanced_confidence": 0.6695,
      "actual": 0,
      "enhanced_pnl_pts": -0.3999999999998636,
      "gate_reason": "soft_adjust",
      "gate_strength": -0.013117
    },
    {
      "ts": "2026-05-08 14:47:00",
      "baseline_direction": 1,
      "baseline_confidence": 0.43,
      "enhanced_direction": 1,
      "enhanced_confidence": 0.4359,
      "actual": -1,
      "enhanced_pnl_pts": -1.2999999999999545,
      "gate_reason": "soft_adjust",
      "gate_strength": 0.148575
    },
    {
      "ts": "2026-05-08 14:48:00",
      "baseline_direction": 1,
      "baseline_confidence": 0.45,
      "enhanced_direction": 1,
      "enhanced_confidence": 0.4546,
      "actual": -1,
      "enhanced_pnl_pts": -1.5499999999999545,
      "gate_reason": "soft_adjust",
      "gate_strength": 0.113757
    },
    {
      "ts": "2026-05-08 14:49:00",
      "baseline_direction": 1,
      "baseline_confidence": 0.4167,
      "enhanced_direction": 1,
      "enhanced_confidence": 0.4203,
      "actual": 0,
      "enhanced_pnl_pts": -0.25,
      "gate_reason": "soft_adjust",
      "gate_strength": 0.09185
    },
    {
      "ts": "2026-05-08 14:50:00",
      "baseline_direction": 1,
      "baseline_confidence": 0.6667,
      "enhanced_direction": 1,
      "enhanced_confidence": 0.6655,
      "actual": 0,
      "enhanced_pnl_pts": -0.34999999999990905,
      "gate_reason": "soft_adjust",
      "gate_strength": -0.029289
    },
    {
      "ts": "2026-05-08 14:51:00",
      "baseline_direction": 1,
      "baseline_confidence": 0.65,
      "enhanced_direction": 1,
      "enhanced_confidence": 0.6492,
      "actual": 0,
      "enhanced_pnl_pts": -0.049999999999954525,
      "gate_reason": "soft_adjust",
      "gate_strength": -0.019186
    },
    {
      "ts": "2026-05-08 14:53:00",
      "baseline_direction": -1,
      "baseline_confidence": 0.58,
      "enhanced_direction": -1,
      "enhanced_confidence": 0.5786,
      "actual": 0,
      "enhanced_pnl_pts": 0.40000000000009095,
      "gate_reason": "soft_adjust",
      "gate_strength": -0.036005
    },
    {
      "ts": "2026-05-08 14:56:00",
      "baseline_direction": -1,
      "baseline_confidence": 0.495,
      "enhanced_direction": -1,
      "enhanced_confidence": 0.4942,
      "actual": -1,
      "enhanced_pnl_pts": 1.300000000000182,
      "gate_reason": "soft_adjust",
      "gate_strength": -0.019932
    },
    {
      "ts": "2026-05-08 14:57:00",
      "baseline_direction": 1,
      "baseline_confidence": 0.6167,
      "enhanced_direction": 1,
      "enhanced_confidence": 0.6138,
      "actual": 0,
      "enhanced_pnl_pts": -0.20000000000004547,
      "gate_reason": "soft_adjust",
      "gate_strength": -0.072646
    }
  ]
}